LICENSE
MANIFEST.in
README.md
setup.py
python_project_generator/__init__.py
python_project_generator/generator.py
python_project_generator.egg-info/PKG-INFO
python_project_generator.egg-info/SOURCES.txt
python_project_generator.egg-info/dependency_links.txt
python_project_generator.egg-info/entry_points.txt
python_project_generator.egg-info/not-zip-safe
python_project_generator.egg-info/top_level.txt
python_project_generator/template/{{project_name}}/LICENSE
python_project_generator/template/{{project_name}}/MANIFEST.in
python_project_generator/template/{{project_name}}/Makefile
python_project_generator/template/{{project_name}}/README.md
python_project_generator/template/{{project_name}}/requirements.txt
python_project_generator/template/{{project_name}}/setup.py.tmpl
python_project_generator/template/{{project_name}}/tests/__init__.py.tmpl
python_project_generator/template/{{project_name}}/tests/context.py.tmpl
python_project_generator/template/{{project_name}}/tests/test_sample.py.tmpl
python_project_generator/template/{{project_name}}/{{project_name}}/__init__.py.tmpl
python_project_generator/template/{{project_name}}/{{project_name}}/core.py.tmpl