Metadata-Version: 1.1
Name: python-project-generator
Version: 0.0.2
Summary: generate a python project
Home-page: https://github.com/slumber1122/python_project_generator
Author: slumber1122
Author-email: slumber1122@gmail.com
License: MIT License
